LICENSE
MANIFEST.in
NOTICE
README.md
requirements.txt
setup.cfg
setup.py
compiler/__init__.py
compiler/api/__init__.py
compiler/api/compiler.py
compiler/api/source/auth_key.tl
compiler/api/source/main_api.tl
compiler/api/source/sys_msgs.tl
compiler/api/template/combinator.txt
compiler/api/template/type.txt
compiler/errors/__init__.py
compiler/errors/compiler.py
compiler/errors/sort.py
compiler/errors/source/303_SEE_OTHER.tsv
compiler/errors/source/400_BAD_REQUEST.tsv
compiler/errors/source/401_UNAUTHORIZED.tsv
compiler/errors/source/403_FORBIDDEN.tsv
compiler/errors/source/406_NOT_ACCEPTABLE.tsv
compiler/errors/source/420_FLOOD.tsv
compiler/errors/source/500_INTERNAL_SERVER_ERROR.tsv
compiler/errors/source/503_SERVICE_UNAVAILABLE.tsv
compiler/errors/template/class.txt
compiler/errors/template/sub_class.txt
darmilibs/__init__.py
darmilibs/client.py
darmilibs/dispatcher.py
darmilibs/emoji.py
darmilibs/file_id.py
darmilibs/filters.py
darmilibs/mime_types.py
darmilibs/py.typed
darmilibs/sync.py
darmilibs/utils.py
darmilibs.egg-info/PKG-INFO
darmilibs.egg-info/SOURCES.txt
darmilibs.egg-info/dependency_links.txt
darmilibs.egg-info/not-zip-safe
darmilibs.egg-info/requires.txt
darmilibs.egg-info/top_level.txt
darmilibs/connection/__init__.py
darmilibs/connection/connection.py
darmilibs/connection/transport/__init__.py
darmilibs/connection/transport/tcp/__init__.py
darmilibs/connection/transport/tcp/tcp.py
darmilibs/connection/transport/tcp/tcp_abridged.py
darmilibs/connection/transport/tcp/tcp_abridged_o.py
darmilibs/connection/transport/tcp/tcp_full.py
darmilibs/connection/transport/tcp/tcp_intermediate.py
darmilibs/connection/transport/tcp/tcp_intermediate_o.py
darmilibs/crypto/__init__.py
darmilibs/crypto/aes.py
darmilibs/crypto/mtproto.py
darmilibs/crypto/prime.py
darmilibs/crypto/rsa.py
darmilibs/darmi/__init__.py
darmilibs/darmi/database/__init__.py
darmilibs/darmi/database/gbandb.py
darmilibs/darmi/database/gmutedb.py
darmilibs/darmi/database/pmpermitdb.py
darmilibs/darmi/database/rraid.py
darmilibs/darmi/helper/PyroHelpers.py
darmilibs/darmi/helper/__init__.py
darmilibs/darmi/helper/adminHelpers.py
darmilibs/darmi/helper/aiohttp_helper.py
